omaha/__init__.py
omaha/client.py
omaha/company.py
omaha/indicator.py
omaha/joinable.py
omaha/omaha.py
omaha/version.py
omaha/tests/__init__.py
omaha/tests/joinable_test.py
omaha/tests/test_client.py
omaha/tests/test_company.py
omaha/tests/test_indicator.py
omaha-0.0.16.dist-info/LICENSE
omaha-0.0.16.dist-info/METADATA
omaha-0.0.16.dist-info/WHEEL
omaha-0.0.16.dist-info/top_level.txt
omaha-0.0.16.dist-info/RECORD
