Metadata-Version: 2.1
Name: omaha
Version: 0.0.16
Summary: Unified view of financial metrics of public companies
Home-page: https://github.com/Lewuathe/omaha
Author: Kai Sasaki
License: Apache License, Version 2.0
Keywords: finance,buffett-code,quandl
Platform: UNKNOWN
Classifier: Programming Language :: Python :: 3
Classifier: Programming Language :: Python :: 3.7
Classifier: Development Status :: 2 - Pre-Alpha
Classifier: License :: OSI Approved :: Apache Software License
Classifier: Topic :: Office/Business :: Financial :: Investment
Requires-Dist: requests
Requires-Dist: pandas
Requires-Dist: cachetools
Requires-Dist: quandl
Requires-Dist: inflection
